dune/__init__.py
dune/__main__.py
dune/config_generator.py
dune/genconfig.py
dune/interactive_dune.py
dune/interactive_mapper.py
dune/llm_analyzer.py
dune/processor_engine.py
dune/smart_env_manager.py
dune/task_validator.py
emllm_dune-0.1.4.dist-info/LICENSE
emllm_dune-0.1.4.dist-info/METADATA
emllm_dune-0.1.4.dist-info/WHEEL
emllm_dune-0.1.4.dist-info/entry_points.txt
emllm_dune-0.1.4.dist-info/RECORD
