Metadata-Version: 2.3
Name: emllm-dune
Version: 0.1.4
Summary: Dynamiczny procesor danych z automatycznym wykrywaniem bibliotek
License: MIT
Author: Tom Sapletta
Author-email: info@softreck.dev
Requires-Python: >=3.11,<4.0
Classifier: License :: OSI Approved :: MIT License
Classifier: Programming Language :: Python :: 3
Classifier: Programming Language :: Python :: 3.11
Classifier: Programming Language :: Python :: 3.12
Classifier: Programming Language :: Python :: 3.13
Requires-Dist: Pillow (>=10.0.0,<11.0.0)
Requires-Dist: beautifulsoup4 (>=4.12.0,<5.0.0)
Requires-Dist: fastapi (>=0.104.1,<0.105.0)
Requires-Dist: jinja2 (>=3.1.2,<4.0.0)
Requires-Dist: loguru (>=0.7.2,<0.8.0)
Requires-Dist: lxml (>=4.9.0,<5.0.0)
Requires-Dist: pandas (>=2.0.0,<3.0.0)
Requires-Dist: pydantic (>=2.5.0,<3.0.0)
Requires-Dist: python-dateutil (>=2.8.2,<3.0.0)
Requires-Dist: python-dotenv (>=1.0.0,<2.0.0)
Requires-Dist: python-magic (>=0.4.27,<0.5.0)
Requires-Dist: pytz (>=2023.3,<2024.0)
Requires-Dist: requests (>=2.31.0,<3.0.0)
Requires-Dist: tqdm (>=4.66.0,<5.0.0)
Requires-Dist: ujson (>=5.8.0,<6.0.0)
Requires-Dist: uvicorn[standard] (>=0.24.0,<0.25.0)
